yhb/__init__.py
yhb/ybasic/__init__.py
yhb/ybasic/ybloomfilter.py
yhb/ybasic/yfile.py
yhb/ybasic/yparallel.py
yhb/ybasic/yrandom.py
yhb/ybasic/ysimhash.py
yhb/ybasic/ytypecheck.py
yhb/ybasic/ywrapper.py
yhb/ycrack/__init__.py
yhb/ycrack/yjiasule.py
yhb/ycrack/ysojson.py
yhb/ycrack/ywenshu.py
yhb/ydb/__init__.py
yhb/ydb/ymysql.py
yhb/ydb/yredis.py
yhb/yhtml/__init__.py
yhb/yhtml/ynextpagejs.py
yhb/yhtml/ytag.py
yhb-0.1.12.dist-info/DESCRIPTION.rst
yhb-0.1.12.dist-info/METADATA
yhb-0.1.12.dist-info/RECORD
yhb-0.1.12.dist-info/WHEEL
yhb-0.1.12.dist-info/metadata.json
yhb-0.1.12.dist-info/top_level.txt
