Metadata-Version: 2.0
Name: yhb
Version: 0.1.12
Summary: A package for quick using utils
Home-page: https://github.com/Jiramew/spoon
Author: Jiramew
Author-email: hanbingflying@sina.com
License: BSD License
Platform: all
Classifier: Development Status :: 3 - Alpha
Classifier: License :: OSI Approved :: BSD License
Classifier: Programming Language :: Python
Classifier: Programming Language :: Python :: 3
Classifier: Programming Language :: Python :: 3.6
Classifier: Programming Language :: Python :: 3.7
Classifier: Topic :: Software Development :: Libraries
Requires-Dist: pymysql (>=0.8.0)
Requires-Dist: redis
Requires-Dist: requests
Requires-Dist: pycryptodomex
Requires-Dist: zhon
Requires-Dist: simhash
Requires-Dist: jieba
